Metadata-Version: 2.1
Name: EasyDiscordWebhookMessage
Version: 1.0.3
Summary: A Python package for easily sending messages through Discord webhooks
Home-page: https://github.com/Axel-Pion-MDS/M2_Discord_Webhook
Author: Maengdok
Author-email: maengdok@outlook.com
Classifier: Development Status :: 3 - Alpha
Classifier: Intended Audience :: Developers
Classifier: License :: OSI Approved :: MIT License
Classifier: Programming Language :: Python :: 3
Classifier: Programming Language :: Python :: 3.6
Classifier: Programming Language :: Python :: 3.7
Classifier: Programming Language :: Python :: 3.8
